braintrust_langchain/__init__.py
braintrust_langchain/callbacks.py
braintrust_langchain/context.py
braintrust_langchain/version.py
tests/__init__.py
tests/conftest.py
tests/helpers.py
tests/test_anthropic.py
tests/test_callbacks.py
tests/test_context.py
tests/types.py
braintrust_langchain-0.2.1.dist-info/METADATA
braintrust_langchain-0.2.1.dist-info/WHEEL
braintrust_langchain-0.2.1.dist-info/top_level.txt
braintrust_langchain-0.2.1.dist-info/RECORD
