Metadata-Version: 2.4
Name: braintrust-langchain
Version: 0.2.1
Summary: Integration for LangChain and Braintrust Tracing
Author-email: Braintrust <info@braintrust.dev>
License-Expression: MIT
Project-URL: Homepage, https://www.braintrust.dev
Project-URL: Repository, https://github.com/braintrustdata/braintrust-sdk
Keywords: braintrust,langchain,llm,tracing,ai,agents
Classifier: Development Status :: 4 - Beta
Classifier: Programming Language :: Python :: 3
Classifier: Programming Language :: Python :: 3.10
Classifier: Programming Language :: Python :: 3.11
Classifier: Programming Language :: Python :: 3.12
Classifier: Operating System :: OS Independent
Requires-Python: >=3.10
Requires-Dist: braintrust>=0.2.1
Requires-Dist: langchain>=0.3.27
